oculive.py
oculive-0.1.dist-info/licenses/LICENSE
oculive-0.1.dist-info/METADATA
oculive-0.1.dist-info/WHEEL
oculive-0.1.dist-info/entry_points.txt
oculive-0.1.dist-info/top_level.txt
oculive-0.1.dist-info/RECORD
